axigen/cli2/__init__.py
axigen/cli2/cli2.py
axigen-0.1.0.dist-info/METADATA
axigen-0.1.0.dist-info/WHEEL
axigen-0.1.0.dist-info/top_level.txt
axigen-0.1.0.dist-info/RECORD
