Metadata-Version: 2.1
Name: axigen
Version: 0.1.0
Summary: Python library for automating Axigen administration tasks
Author: Axigen Messaging
Author-email: info@axigen.com
Classifier: Programming Language :: Python :: 3
Classifier: License :: OSI Approved :: BSD License
Classifier: Operating System :: OS Independent
Requires-Python: >=3.6
